LICENSE.txt
MANIFEST.in
readme.md
requirements.txt
setup.py
AC_Flask_HipChat.egg-info/PKG-INFO
AC_Flask_HipChat.egg-info/SOURCES.txt
AC_Flask_HipChat.egg-info/dependency_links.txt
AC_Flask_HipChat.egg-info/not-zip-safe
AC_Flask_HipChat.egg-info/requires.txt
AC_Flask_HipChat.egg-info/top_level.txt
ac_flask/__init__.py
ac_flask/hipchat/__init__.py
ac_flask/hipchat/addon.py
ac_flask/hipchat/auth.py
ac_flask/hipchat/clients.py
ac_flask/hipchat/db.py
ac_flask/hipchat/default_settings.py
ac_flask/hipchat/events.py
ac_flask/hipchat/glance.py
ac_flask/hipchat/installable.py
ac_flask/hipchat/tenant.py