Metadata-Version: 1.1
Name: AC-Flask-HipChat
Version: 0.2.8
Summary: Atlassian Connect library based on Flask for HipChat
Home-page: https://bitbucket.org/atlassianlabs/ac-flask-hipchat
Author: Don Brown
Author-email: mrdon@twdata.org
License: APLv2
Platform: any
Classifier: Environment :: Web Environment
Classifier: Intended Audience :: Developers
Classifier: License :: OSI Approved :: BSD License
Classifier: Operating System :: OS Independent
Classifier: Programming Language :: Python
Classifier: Topic :: Internet :: WWW/HTTP :: Dynamic Content
Classifier: Topic :: Software Development :: Libraries :: Python Modules
